faust_avro_codec_codegen/README.md
faust_avro_codec_codegen/__init__.py
faust_avro_codec_codegen/__main__.py
faust_avro_codec_codegen/main.py
faust_avro_codec_codegen/settings.py
faust_avro_codec_codegen/templates/topics.py.jinja2
faust_avro_codec_codegen-0.1.0.dist-info/LICENSE
faust_avro_codec_codegen-0.1.0.dist-info/METADATA
faust_avro_codec_codegen-0.1.0.dist-info/WHEEL
faust_avro_codec_codegen-0.1.0.dist-info/RECORD
