Metadata-Version: 2.1
Name: faust-avro-codec-codegen
Version: 0.1.0
Summary: 
Author: brad.boggs
Author-email: bboggs@streambit.software
Requires-Python: >=3.10,<4.0
Classifier: Programming Language :: Python :: 3
Classifier: Programming Language :: Python :: 3.10
Classifier: Programming Language :: Python :: 3.11
Requires-Dist: faust-avro-model-codegen (>=0.1.7,<0.2.0)
